bssl-1.0.0a0.dist-info/METADATA
bssl-1.0.0a0.dist-info/WHEEL
bssl-1.0.0a0.dist-info/licenses/LICENSE
bssl.libs/libgcc_s-0366c7ba.so.1
bssl/__init__.py
bssl/bssl.cpython-313t-arm-linux-musleabihf.so
bssl/bssl.pyi
bssl/conf.py
bssl/enums.py
bssl/err.py
bssl/impl.py
bssl/store.py
bssl-1.0.0a0.dist-info/RECORD
