Metadata-Version: 2.4
Name: bssl
Version: 1.0.0a0
Classifier: Programming Language :: Python
Classifier: Programming Language :: Rust
Classifier: Typing :: Typed
Classifier: Intended Audience :: Developers
Classifier: Intended Audience :: Information Technology
Classifier: Topic :: Software Development
Classifier: Topic :: Software Development :: Libraries
Classifier: Topic :: Software Development :: Libraries :: Python Modules
Classifier: Programming Language :: Python :: 3
Classifier: Programming Language :: Python :: 3 :: Only
Classifier: Programming Language :: Python :: 3.12
Classifier: Programming Language :: Python :: 3.13
Classifier: Operating System :: Microsoft :: Windows
Classifier: Operating System :: POSIX
Classifier: Operating System :: Unix
Classifier: Operating System :: MacOS
Classifier: Development Status :: 3 - Alpha
License-File: LICENSE
Summary: Modern and flexible TLS for Python, built on BoringSSL
Keywords: tls,ja3,ja4,fingerprint
Author-email: Dmytro Tkachenko <itsme@somespecial.one>
License-Expression: Apache-2.0
Requires-Python: >=3.12
Project-URL: Homepage, https://github.com/somespecialone/bssl
Project-URL: Documentation, https://github.com/somespecialone/bssl
Project-URL: Repository, https://github.com/somespecialone/bssl/
Project-URL: Bug Tracker, https://github.com/somespecialone/bssl/issues
